{
  "type": "pattern",
  "slug": "rabin-karp-algorithm",
  "name": "Rabin Karp Algorithm",
  "description": "Master the Rabin Karp Algorithm coding pattern with curated problems.",
  "problemCount": 20,
  "problemSlugs": [
    "repeated-string-match",
    "rotate-string",
    "longest-duplicate-substring",
    "longest-repeating-substring",
    "longest-chunked-palindrome-decomposition",
    "maximum-number-of-occurrences-of-a-substring",
    "distinct-echo-substrings",
    "longest-happy-prefix",
    "strings-differ-by-one-character",
    "longest-common-subpath",
    "find-substring-with-given-hash-value",
    "unique-substrings-with-equal-digit-frequency",
    "k-divisible-elements-subarrays",
    "maximum-deletions-on-a-string",
    "equalize-strings-by-adding-or-removing-characters-at-ends",
    "minimum-number-of-valid-strings-to-form-target-i",
    "minimum-number-of-valid-strings-to-form-target-ii",
    "lexicographically-smallest-string-after-reverse",
    "lexicographically-smallest-string-after-reverse-ii",
    "smallest-unique-subarray"
  ],
  "relatedTopics": [],
  "seo": {
    "title": "Rabin Karp Algorithm Pattern — Problems & Guide | AlgoForge",
    "description": "Learn the Rabin Karp Algorithm pattern with 20 practice problems, interview tips, and visual intuition.",
    "keywords": [
      "Rabin Karp Algorithm",
      "Rabin Karp Algorithm pattern",
      "Rabin Karp Algorithm leetcode",
      "coding patterns"
    ],
    "canonicalPath": "/patterns/rabin-karp-algorithm"
  }
}